hisql/__init__.py
hisql/himodule.py
hisql-0.0.2.dist-info/LICENSE
hisql-0.0.2.dist-info/METADATA
hisql-0.0.2.dist-info/WHEEL
hisql-0.0.2.dist-info/top_level.txt
hisql-0.0.2.dist-info/RECORD
