Metadata-Version: 2.1
Name: hisql
Version: 0.0.2
Summary: 纯SQL操作数据库
Home-page: https://github.com/buf1024/hisql
License: UNKNOWN
Platform: UNKNOWN
Classifier: Programming Language :: Python :: 3
Classifier: License :: OSI Approved :: MIT License
Classifier: Operating System :: OS Independent
Requires-Dist: pugsql
Requires-Dist: pandas
